{
	"info": {
		"_postman_id": "088e0820-257b-40f3-af96-3c1a8b88d06a",
		"name": "Postman_Collection",
		"schema": "https://schema.getpostman.com/json/collection/v2.1.0/collection.json"
	},
	"item": [
		{
			"name": "Authorization_1",
			"event": [
				{
					"listen": "test",
					"script": {
						"exec": [
							"var body = JSON.parse(responseBody)\r",
							"\r",
							"pm.collectionVariables.set(\"token1\", body.access_token);\r",
							"\r",
							"pm.test(\"Status code is 200\", function () {\r",
							"    pm.response.to.have.status(200);\r",
							"});"
						],
						"type": "text/javascript"
					}
				}
			],
			"request": {
				"method": "POST",
				"header": [],
				"body": {
					"mode": "formdata",
					"formdata": [
						{
							"key": "username",
							"value": "Username_1",
							"type": "text"
						},
						{
							"key": "password",
							"value": "Password_Name_1",
							"type": "text"
						},
						{
							"key": "grant_type",
							"value": "password",
							"type": "text"
						}
					]
				},
				"url": {
					"raw": "https://radio-shop.megaplan.by/api/v3/auth/access_token",
					"protocol": "https",
					"host": [
						"radio-shop",
						"megaplan",
						"by"
					],
					"path": [
						"api",
						"v3",
						"auth",
						"access_token"
					]
				}
			},
			"response": []
		},
		{
			"name": "Authorization_2",
			"event": [
				{
					"listen": "test",
					"script": {
						"exec": [
							"var body = JSON.parse(responseBody)\r",
							"\r",
							"pm.collectionVariables.set(\"token2\", body.access_token);\r",
							"\r",
							"pm.test(\"Status code is 200\", function () {\r",
							"    pm.response.to.have.status(200);\r",
							"});"
						],
						"type": "text/javascript"
					}
				}
			],
			"request": {
				"method": "POST",
				"header": [],
				"body": {
					"mode": "formdata",
					"formdata": [
						{
							"key": "username",
							"value": "Username_2",
							"type": "text"
						},
						{
							"key": "password",
							"value": "Password_Name_2",
							"type": "text"
						},
						{
							"key": "grant_type",
							"value": "password",
							"type": "text"
						}
					]
				},
				"url": {
					"raw": "https://radio-shop.megaplan.by/api/v3/auth/access_token",
					"protocol": "https",
					"host": [
						"radio-shop",
						"megaplan",
						"by"
					],
					"path": [
						"api",
						"v3",
						"auth",
						"access_token"
					]
				}
			},
			"response": []
		},
		{
			"name": "Create_Task",
			"event": [
				{
					"listen": "test",
					"script": {
						"exec": [
							"var body = JSON.parse(responseBody)\r",
							"\r",
							"pm.collectionVariables.set(\"Task\", body.data.id);\r",
							"\r",
							"pm.test(\"Status code is 200\", function () {\r",
							"    pm.response.to.have.status(200);\r",
							"});\r",
							"pm.test(\"Task name\", function () {\r",
							"    var jsonData = pm.response.json();\r",
							"    pm.expect(jsonData.data.name).to.eql(\"Task_1\");\r",
							"});\r",
							"pm.test(\"Task responsible\", function () {\r",
							"    var jsonData = pm.response.json();\r",
							"    pm.expect(jsonData.data.responsible.name).to.eql(\"Testing2 Exploratory\");\r",
							"});\r",
							"pm.test(\"Task status\", function () {\r",
							"    var jsonData = pm.response.json();\r",
							"    pm.expect(jsonData.data.status).to.eql(\"assigned\");\r",
							"});\r",
							"pm.collectionVariables.set(\"variable_key\", \"variable_value\");"
						],
						"type": "text/javascript"
					}
				}
			],
			"request": {
				"method": "POST",
				"header": [
					{
						"key": "Authorization",
						"value": "Bearer {{token1}}",
						"type": "text"
					}
				],
				"body": {
					"mode": "raw",
					"raw": "{\r\n    \"contentType\": \"Task\",\r\n    \"name\": \"Task_1\",\r\n    \"deadline\": null,\r\n    \"parent\": null,\r\n    \"isUrgent\": false,\r\n    \"isTemplate\": false,\r\n    \"owner\": {\r\n        \"id\": \"1000104\",\r\n        \"contentType\": \"Employee\"\r\n    },\r\n    \"responsible\": {\r\n        \"id\": \"1000105\",\r\n        \"contentType\": \"Employee\"\r\n    },\r\n    \"contractor\": null,\r\n    \"attaches\": [],\r\n    \"Category130CustomFieldDlyaTesta\": null,\r\n    \"Category130CustomFieldTest2\": null\r\n}",
					"options": {
						"raw": {
							"language": "json"
						}
					}
				},
				"url": {
					"raw": "https://radio-shop.megaplan.by/api/v3/task",
					"protocol": "https",
					"host": [
						"radio-shop",
						"megaplan",
						"by"
					],
					"path": [
						"api",
						"v3",
						"task"
					]
				}
			},
			"response": []
		},
		{
			"name": "Add_Task_Description",
			"event": [
				{
					"listen": "test",
					"script": {
						"exec": [
							"pm.test(\"Status code is 200\", function () {\r",
							"    pm.response.to.have.status(200);\r",
							"});\r",
							"pm.test(\"Task description\", function () {\r",
							"    var jsonData = pm.response.json();\r",
							"    pm.expect(jsonData.data.textStatement).to.eql(\"Описание задачи следующее: новая задача!\");\r",
							"});"
						],
						"type": "text/javascript"
					}
				}
			],
			"request": {
				"method": "POST",
				"header": [
					{
						"key": "Authorization",
						"value": "Bearer {{token1}}",
						"type": "text"
					}
				],
				"body": {
					"mode": "raw",
					"raw": "{\r\n    \"id\": \"1005623\",\r\n    \"contentType\": \"Task\",\r\n    \"attaches\": [],\r\n    \"statement\": \"<p>Описание задачи следующее: новая задача!</p>\"\r\n}",
					"options": {
						"raw": {
							"language": "json"
						}
					}
				},
				"url": {
					"raw": "https://radio-shop.megaplan.by/api/v3/task/{{Task}}",
					"protocol": "https",
					"host": [
						"radio-shop",
						"megaplan",
						"by"
					],
					"path": [
						"api",
						"v3",
						"task",
						"{{Task}}"
					]
				}
			},
			"response": []
		},
		{
			"name": "Accept_Task",
			"event": [
				{
					"listen": "test",
					"script": {
						"exec": [
							"pm.test(\"Status code is 200\", function () {\r",
							"    pm.response.to.have.status(200);\r",
							"});\r",
							"pm.test(\"Task status\", function () {\r",
							"    var jsonData = pm.response.json();\r",
							"    pm.expect(jsonData.data.status).to.eql(\"accepted\");\r",
							"});"
						],
						"type": "text/javascript"
					}
				}
			],
			"request": {
				"method": "POST",
				"header": [
					{
						"key": "Authorization",
						"value": "Bearer {{token2}}",
						"type": "text"
					}
				],
				"body": {
					"mode": "raw",
					"raw": "{\r\n    \"action\": \"act_accept_task\",\r\n    \"checkTodos\": false\r\n}",
					"options": {
						"raw": {
							"language": "json"
						}
					}
				},
				"url": {
					"raw": "https://radio-shop.megaplan.by/api/v3/task/{{Task}}/doAction",
					"protocol": "https",
					"host": [
						"radio-shop",
						"megaplan",
						"by"
					],
					"path": [
						"api",
						"v3",
						"task",
						"{{Task}}",
						"doAction"
					]
				}
			},
			"response": []
		},
		{
			"name": "Complete_Task",
			"event": [
				{
					"listen": "test",
					"script": {
						"exec": [
							"pm.test(\"Status code is 200\", function () {\r",
							"    pm.response.to.have.status(200);\r",
							"});\r",
							"pm.test(\"Task status\", function () {\r",
							"    var jsonData = pm.response.json();\r",
							"    pm.expect(jsonData.data.status).to.eql(\"done\");\r",
							"});"
						],
						"type": "text/javascript"
					}
				}
			],
			"request": {
				"method": "POST",
				"header": [
					{
						"key": "Authorization",
						"value": "Bearer {{token2}}",
						"type": "text"
					}
				],
				"body": {
					"mode": "raw",
					"raw": "{\r\n    \"action\": \"act_done\",\r\n    \"checkTodos\": true\r\n}",
					"options": {
						"raw": {
							"language": "json"
						}
					}
				},
				"url": {
					"raw": "https://radio-shop.megaplan.by/api/v3/task/{{Task}}/doAction",
					"protocol": "https",
					"host": [
						"radio-shop",
						"megaplan",
						"by"
					],
					"path": [
						"api",
						"v3",
						"task",
						"{{Task}}",
						"doAction"
					]
				}
			},
			"response": []
		},
		{
			"name": "Comment_to_Completed_Task",
			"event": [
				{
					"listen": "test",
					"script": {
						"exec": [
							"pm.test(\"Status code is 200\", function () {\r",
							"    pm.response.to.have.status(200);\r",
							"});\r",
							"pm.test(\"Comment\", function () {\r",
							"    var jsonData = pm.response.json();\r",
							"    pm.expect(jsonData.data.content).to.eql(\"<p>Второй комментарий к задаче</p>\");\r",
							"});"
						],
						"type": "text/javascript"
					}
				}
			],
			"request": {
				"method": "POST",
				"header": [
					{
						"key": "Authorization",
						"value": "Bearer {{token2}}",
						"type": "text"
					}
				],
				"body": {
					"mode": "raw",
					"raw": "{\r\n    \"contentType\": \"CommentCreateActionRequest\",\r\n    \"comment\": {\r\n        \"contentType\": \"Comment\",\r\n        \"content\": \"<p>Второй комментарий к задаче</p>\",\r\n        \"attaches\": [],\r\n        \"workTime\": null,\r\n        \"workDate\": {\r\n            \"contentType\": \"DateTime\",\r\n            \"value\": \"2022-03-22T18:07:21.630Z\"\r\n        },\r\n        \"completed\": 0,\r\n        \"owner\": {\r\n            \"id\": \"1000105\",\r\n            \"contentType\": \"Employee\"\r\n        },\r\n        \"subject\": {\r\n            \"id\": \"1005606\",\r\n            \"contentType\": \"Task\"\r\n        },\r\n        \"timeCreated\": {\r\n            \"contentType\": \"DateTime\",\r\n            \"value\": \"2022-03-22T18:19:16.005Z\"\r\n        }\r\n    },\r\n    \"transports\": [\r\n        {}\r\n    ]\r\n}",
					"options": {
						"raw": {
							"language": "json"
						}
					}
				},
				"url": {
					"raw": "https://radio-shop.megaplan.by/api/v3/task/{{Task}}/comments",
					"protocol": "https",
					"host": [
						"radio-shop",
						"megaplan",
						"by"
					],
					"path": [
						"api",
						"v3",
						"task",
						"{{Task}}",
						"comments"
					]
				}
			},
			"response": []
		},
		{
			"name": "Accept_Task",
			"event": [
				{
					"listen": "test",
					"script": {
						"exec": [
							"pm.test(\"Status code is 200\", function () {\r",
							"    pm.response.to.have.status(200);\r",
							"});\r",
							"pm.test(\"Task status\", function () {\r",
							"    var jsonData = pm.response.json();\r",
							"    pm.expect(jsonData.data.status).to.eql(\"completed\");\r",
							"});"
						],
						"type": "text/javascript"
					}
				}
			],
			"request": {
				"method": "POST",
				"header": [
					{
						"key": "Authorization",
						"value": "Bearer {{token1}}",
						"type": "text"
					}
				],
				"body": {
					"mode": "raw",
					"raw": "{\r\n    \"action\": \"act_accept_work\",\r\n    \"checkTodos\": true\r\n}",
					"options": {
						"raw": {
							"language": "json"
						}
					}
				},
				"url": {
					"raw": "https://radio-shop.megaplan.by/api/v3/task/{{Task}}/doAction",
					"protocol": "https",
					"host": [
						"radio-shop",
						"megaplan",
						"by"
					],
					"path": [
						"api",
						"v3",
						"task",
						"{{Task}}",
						"doAction"
					]
				}
			},
			"response": []
		},
		{
			"name": "Delete_Task",
			"event": [
				{
					"listen": "test",
					"script": {
						"exec": [
							"pm.test(\"Status code is 200\", function () {\r",
							"    pm.response.to.have.status(200);\r",
							"});\r",
							"pm.test(\"Text in body\", function () {\r",
							"    var jsonData = pm.response.json();\r",
							"    pm.expect(jsonData.data).to.eql(\"Task successfully removed\");\r",
							"});"
						],
						"type": "text/javascript"
					}
				}
			],
			"request": {
				"method": "DELETE",
				"header": [
					{
						"key": "Authorization",
						"value": "Bearer {{token1}}",
						"type": "text"
					}
				],
				"body": {
					"mode": "raw",
					"raw": "{}",
					"options": {
						"raw": {
							"language": "json"
						}
					}
				},
				"url": {
					"raw": "https://radio-shop.megaplan.by/api/v3/task/{{Task}}",
					"protocol": "https",
					"host": [
						"radio-shop",
						"megaplan",
						"by"
					],
					"path": [
						"api",
						"v3",
						"task",
						"{{Task}}"
					]
				}
			},
			"response": []
		}
	],
	"variable": [
		{
			"key": "2",
			"value": "NzgyNmI5ZGE1NDY5ZTYyMWQ1NWI0OGY0NGU5YjY5MWZlZjhiNTkzYmU2NjcyOGQyYmRmMzE0NzczZjllMmE3ZQ"
		},
		{
			"key": "1",
			"value": "YTZkYzI1MjdjMDAwMTg3NmY2YTkzZDhlM2NjMWYxYzA4MThhNzZlOGQwZWE4YzJmMTUzMWU4YmI5NDk2ZWMxZg"
		},
		{
			"key": "3",
			"value": "OWY2NTU5YjI0NjJlOTU2ZGRiYmE2NWQ2ZDBiMmMwNzNmOWZjZWUzODljNzAwNDkwZWI0ZmY5OGQxNzc3YzJlNw"
		},
		{
			"key": "4",
			"value": "1005735"
		},
		{
			"key": "variable_key",
			"value": ""
		},
		{
			"key": "token1",
			"value": ""
		},
		{
			"key": "token2",
			"value": ""
		},
		{
			"key": "Task",
			"value": ""
		}
	]
}